cafeto/__init__.py
cafeto/app.py
cafeto/types.py
cafeto/authentication/__init__.py
cafeto/authentication/requires.py
cafeto/background/__init__.py
cafeto/convertors/__init__.py
cafeto/datastructures/__init__.py
cafeto/dependency_injection/__init__.py
cafeto/dependency_injection/service_collection.py
cafeto/dependency_injection/service_provider.py
cafeto/dtos/__init__.py
cafeto/errors/__init__.py
cafeto/errors/errors.py
cafeto/events/__init__.py
cafeto/events/action_events.py
cafeto/middleware/__init__.py
cafeto/models/__init__.py
cafeto/models/base_model.py
cafeto/models/model_creator.py
cafeto/models/model_validator.py
cafeto/models/validator_collection.py
cafeto/mvc/__init__.py
cafeto/mvc/action.py
cafeto/mvc/base_controller.py
cafeto/mvc/endpoint.py
cafeto/mvc/types.py
cafeto/requests/__init__.py
cafeto/requests/request.py
cafeto/responses/__init__.py
cafeto/responses/codes.py
cafeto/responses/formats.py
cafeto/responses/model_response.py
cafeto/responses/unified_response.py
cafeto/routing/__init__.py
cafeto/schema/__init__.py
cafeto/schema/default_docs.py
cafeto/schema/openapi.py
cafeto/schema/library/schema.py
cafeto/services/__init__.py
cafeto/services/context_service.py
cafeto/static/cafeto/swagger-ui-bundle.js
cafeto/static/cafeto/swagger-ui-standalone-preset.js
cafeto/static/cafeto/swagger-ui.css
cafeto/staticfiles/__init__.py
cafeto/templates/cafeto/swagger.html
cafeto/templating/__init__.py
cafeto/testclient/__init__.py
cafeto/websocket/__init__.py
cafeto/websocket/websocket.py
cafeto-0.1.1.dist-info/METADATA
cafeto-0.1.1.dist-info/WHEEL
cafeto-0.1.1.dist-info/entry_points.txt
cafeto-0.1.1.dist-info/licenses/LICENSE
cafeto-0.1.1.dist-info/RECORD
