Metadata-Version: 2.4
Name: cafeto
Version: 0.1.1
Summary: Cafeto is a lightweight yet powerful framework designed as a top layer over Starlette, focusing on simplifying and accelerating the development of modern APIs. It harnesses the robust foundation of Starlette, offering additional tools for more efficient and organized development.
Project-URL: Homepage, https://github.com/if-geek/cafeto
Project-URL: Issues, https://github.com/if-geek/cafeto
Author-email: Jonathan Espinal <jonathan.espinal@gmail.com>
License-Expression: MIT
License-File: LICENSE
Keywords: API,MVC,Starlette,cafeto,plugin
Classifier: Operating System :: OS Independent
Classifier: Programming Language :: Python :: 3
Requires-Python: >=3.10
Requires-Dist: httpx==0.28.1
Requires-Dist: jinja2==3.1.5
Requires-Dist: mkdocs-i18n==0.4.6
Requires-Dist: mkdocs-material-extensions==1.3.1
Requires-Dist: mkdocs-material==9.6.5
Requires-Dist: mkdocs==1.6.1
Requires-Dist: pydantic==2.8.2
Requires-Dist: pytest-asyncio==0.25.3
Requires-Dist: pytest-cov==6.0.0
Requires-Dist: pytest==8.3.4
Requires-Dist: python-multipart==0.0.20
Requires-Dist: pyyaml==6.0.2
Requires-Dist: starlette==0.45.3
Requires-Dist: uvicorn==0.34.0
Requires-Dist: websockets==14.2
